solo/VERSION
solo/__init__.py
solo/client.py
solo/commands.py
solo/dfu.py
solo/enums.py
solo/exceptions.py
solo/helpers.py
solo/hmac_secret.py
solo/operations.py
solo/solotool.py
solo/cli/__init__.py
solo/cli/_checks.py
solo/cli/key.py
solo/cli/monitor.py
solo/cli/program.py
solo/cli/update.py
solo/devices/__init__.py
solo/devices/base.py
solo/devices/solo_v1.py
solo/fido2/__init__.py
solo/fido2/udp_backend.py
solo1-0.1.1.dist-info/entry_points.txt
solo1-0.1.1.dist-info/LICENSE-APACHE
solo1-0.1.1.dist-info/LICENSE-MIT
solo1-0.1.1.dist-info/WHEEL
solo1-0.1.1.dist-info/METADATA
solo1-0.1.1.dist-info/RECORD
