Metadata-Version: 2.1
Name: solo1
Version: 0.1.1
Summary: Python library for SoloKeys.
Home-page: https://github.com/solokeys/solo1-cli
Author: SoloKeys
Author-email: hello@solokeys.com
Requires-Python: >=3.6
Classifier: License :: OSI Approved :: MIT License
Classifier: License :: OSI Approved :: Apache Software License
Classifier: Intended Audience :: Developers
Classifier: Intended Audience :: End Users/Desktop
Classifier: Programming Language :: Python :: 3 :: Only
Classifier: Programming Language :: Python :: 3.6
Classifier: Programming Language :: Python :: 3.7
Classifier: Programming Language :: Python :: 3.8
Classifier: Programming Language :: Python :: 3.9
Classifier: Programming Language :: Python :: 3.10
Requires-Dist: click >= 7.1
Requires-Dist: cryptography
Requires-Dist: ecdsa
Requires-Dist: fido2 >= 0.9.1
Requires-Dist: intelhex
Requires-Dist: pyserial
Requires-Dist: pyusb
Requires-Dist: requests
